uv_lock_report/__init__.py
uv_lock_report/__main__.py
uv_lock_report/cli.py
uv_lock_report/models.py
uv_lock_report/report.py
uv_lock_report/tests/__init__.py
uv_lock_report/tests/conftest.py
uv_lock_report/tests/test_get_lockfiles.py
uv_lock_report/tests/test_lock_file_reporter.py
uv_lock_report/tests/test_lockfile.py
uv_lock_report/tests/test_lockfile_changes.py
uv_lock_report/tests/test_updated_package.py
uv_lock_report/tests/test_version_change_level.py
uv_lock_report-0.12.1.dist-info/METADATA
uv_lock_report-0.12.1.dist-info/WHEEL
uv_lock_report-0.12.1.dist-info/entry_points.txt
uv_lock_report-0.12.1.dist-info/RECORD
