Metadata-Version: 2.4
Name: uv-lock-report
Version: 0.12.1
Summary: Parse and report package changes in uv.lock.
Project-URL: Homepage, https://github.com/mw-root/uv-lock-report
Project-URL: Source, https://github.com/mw-root/uv-lock-report
Requires-Python: >=3.13
Requires-Dist: packaging>=25.0
Requires-Dist: pydantic>=2.11.9
